{
  "_class": "shapePath",
  "booleanOperation": -1,
  "do_objectID": "E952DD4F-DE8D-484B-BE69-88BEFB948638",
  "edited": true,
  "exportOptions": {
    "_class": "exportOptions",
    "exportFormats": [
    ],
    "includedLayerIds": [
    ],
    "layerOptions": 0,
    "shouldTrim": false
  },
  "frame": {
    "_class": "rect",
    "constrainProportions": false,
    "height": 34.91200000000003,
    "width": 20.16800000000001,
    "x": 0,
    "y": 0
  },
  "isClosed": false,
  "isFlippedHorizontal": false,
  "isFlippedVertical": false,
  "isLocked": false,
  "isVisible": true,
  "layerListExpandedType": 0,
  "name": "Path",
  "nameIsFixed": false,
  "path": {
    "_class": "path",
    "isClosed": false,
    "pointRadiusBehaviour": 1,
    "points": [
      {
        "_class": "curvePoint",
        "cornerRadius": 0,
        "curveFrom": "{0, 0.6665043538038492}",
        "curveMode": 1,
        "curveTo": "{0, 0.6665043538038492}",
        "hasCurveFrom": false,
        "hasCurveTo": false,
        "point": "{0, 0.6665043538038492}"
      },
      {
        "_class": "curvePoint",
        "cornerRadius": 0,
        "curveFrom": "{0, 0}",
        "curveMode": 1,
        "curveTo": "{0, 0}",
        "hasCurveFrom": false,
        "hasCurveTo": false,
        "point": "{0, 0}"
      },
      {
        "_class": "curvePoint",
        "cornerRadius": 0,
        "curveFrom": "{0.99995041650138805, 0.3334956461961508}",
        "curveMode": 1,
        "curveTo": "{0.99995041650138805, 0.3334956461961508}",
        "hasCurveFrom": false,
        "hasCurveTo": false,
        "point": "{0.99995041650138805, 0.3334956461961508}"
      },
      {
        "_class": "curvePoint",
        "cornerRadius": 0,
        "curveFrom": "{1, 1}",
        "curveMode": 1,
        "curveTo": "{1, 1}",
        "hasCurveFrom": false,
        "hasCurveTo": false,
        "point": "{1, 1}"
      },
      {
        "_class": "curvePoint",
        "cornerRadius": 0,
        "curveFrom": "{0, 0.6665043538038492}",
        "curveMode": 1,
        "curveTo": "{0, 0.6665043538038492}",
        "hasCurveFrom": false,
        "hasCurveTo": false,
        "point": "{0, 0.6665043538038492}"
      }
    ]
  },
  "pointRadiusBehaviour": 1,
  "points": [
    {
      "_class": "curvePoint",
      "cornerRadius": 0,
      "curveFrom": "{0, 0.6665043538038492}",
      "curveMode": 1,
      "curveTo": "{0, 0.6665043538038492}",
      "hasCurveFrom": false,
      "hasCurveTo": false,
      "point": "{0, 0.6665043538038492}"
    },
    {
      "_class": "curvePoint",
      "cornerRadius": 0,
      "curveFrom": "{0, 0}",
      "curveMode": 1,
      "curveTo": "{0, 0}",
      "hasCurveFrom": false,
      "hasCurveTo": false,
      "point": "{0, 0}"
    },
    {
      "_class": "curvePoint",
      "cornerRadius": 0,
      "curveFrom": "{0.99995041650138805, 0.3334956461961508}",
      "curveMode": 1,
      "curveTo": "{0.99995041650138805, 0.3334956461961508}",
      "hasCurveFrom": false,
      "hasCurveTo": false,
      "point": "{0.99995041650138805, 0.3334956461961508}"
    },
    {
      "_class": "curvePoint",
      "cornerRadius": 0,
      "curveFrom": "{1, 1}",
      "curveMode": 1,
      "curveTo": "{1, 1}",
      "hasCurveFrom": false,
      "hasCurveTo": false,
      "point": "{1, 1}"
    },
    {
      "_class": "curvePoint",
      "cornerRadius": 0,
      "curveFrom": "{0, 0.6665043538038492}",
      "curveMode": 1,
      "curveTo": "{0, 0.6665043538038492}",
      "hasCurveFrom": false,
      "hasCurveTo": false,
      "point": "{0, 0.6665043538038492}"
    }
  ],
  "resizingConstraint": 63,
  "resizingType": 0,
  "rotation": 0,
  "shouldBreakMaskChain": false
}