{
  "_class": "shapePath",
  "booleanOperation": -1,
  "do_objectID": "078278F2-5B00-4802-BA11-936E8D7AE33E",
  "edited": true,
  "exportOptions": {
    "_class": "exportOptions",
    "exportFormats": [
    ],
    "includedLayerIds": [
    ],
    "layerOptions": 0,
    "shouldTrim": false
  },
  "frame": {
    "_class": "rect",
    "constrainProportions": false,
    "height": 12.9513810808418,
    "width": 7.359937468670635,
    "x": 9.200026054720572,
    "y": 29.60333640736425
  },
  "isClosed": true,
  "isFlippedHorizontal": false,
  "isFlippedVertical": false,
  "isLocked": false,
  "isVisible": true,
  "layerListExpandedType": 0,
  "name": "Path",
  "nameIsFixed": false,
  "path": {
    "_class": "path",
    "isClosed": true,
    "pointRadiusBehaviour": 1,
    "points": [
      {
        "_class": "curvePoint",
        "cornerRadius": 0,
        "curveFrom": "{1, 1}",
        "curveMode": 1,
        "curveTo": "{1, 1}",
        "hasCurveFrom": false,
        "hasCurveTo": false,
        "point": "{1, 1}"
      },
      {
        "_class": "curvePoint",
        "cornerRadius": 0,
        "curveFrom": "{0, 0.71428802615182907}",
        "curveMode": 1,
        "curveTo": "{0, 0.71428802615182907}",
        "hasCurveFrom": false,
        "hasCurveTo": false,
        "point": "{0, 0.71428802615182907}"
      },
      {
        "_class": "curvePoint",
        "cornerRadius": 0,
        "curveFrom": "{0, 0}",
        "curveMode": 1,
        "curveTo": "{0, 0}",
        "hasCurveFrom": false,
        "hasCurveTo": false,
        "point": "{0, 0}"
      },
      {
        "_class": "curvePoint",
        "cornerRadius": 0,
        "curveFrom": "{1, 0.28571197384817004}",
        "curveMode": 1,
        "curveTo": "{1, 0.28571197384817004}",
        "hasCurveFrom": false,
        "hasCurveTo": false,
        "point": "{1, 0.28571197384817004}"
      }
    ]
  },
  "pointRadiusBehaviour": 1,
  "points": [
    {
      "_class": "curvePoint",
      "cornerRadius": 0,
      "curveFrom": "{1, 1}",
      "curveMode": 1,
      "curveTo": "{1, 1}",
      "hasCurveFrom": false,
      "hasCurveTo": false,
      "point": "{1, 1}"
    },
    {
      "_class": "curvePoint",
      "cornerRadius": 0,
      "curveFrom": "{0, 0.71428802615182907}",
      "curveMode": 1,
      "curveTo": "{0, 0.71428802615182907}",
      "hasCurveFrom": false,
      "hasCurveTo": false,
      "point": "{0, 0.71428802615182907}"
    },
    {
      "_class": "curvePoint",
      "cornerRadius": 0,
      "curveFrom": "{0, 0}",
      "curveMode": 1,
      "curveTo": "{0, 0}",
      "hasCurveFrom": false,
      "hasCurveTo": false,
      "point": "{0, 0}"
    },
    {
      "_class": "curvePoint",
      "cornerRadius": 0,
      "curveFrom": "{1, 0.28571197384817004}",
      "curveMode": 1,
      "curveTo": "{1, 0.28571197384817004}",
      "hasCurveFrom": false,
      "hasCurveTo": false,
      "point": "{1, 0.28571197384817004}"
    }
  ],
  "resizingConstraint": 63,
  "resizingType": 0,
  "rotation": 0,
  "shouldBreakMaskChain": false
}